renishaw_wdf-1.4.0.dist-info/licenses/LICENSE
wdf/__init__.py
wdf/custom.py
wdf/origin.py
wdf/predefinedKeys.py
wdf/pset.py
wdf/py.typed
wdf/wdf.py
wdf/wdfenums.py
wdf/browser/__init__.py
wdf/browser/__main__.py
wdf/browser/wireimage.py
renishaw_wdf-1.4.0.dist-info/METADATA
renishaw_wdf-1.4.0.dist-info/WHEEL
renishaw_wdf-1.4.0.dist-info/entry_points.txt
renishaw_wdf-1.4.0.dist-info/top_level.txt
renishaw_wdf-1.4.0.dist-info/RECORD
