Metadata-Version: 2.4
Name: renishaw_wdf
Version: 1.4.0
Summary: Renishaw spectroscopy data file accessor classes
Author: Renishaw Spectroscopy
Author-email: Raman.Support@renishaw.com
License: Apache-2.0
Platform: any
Classifier: Development Status :: 5 - Production/Stable
Classifier: Intended Audience :: Science/Research
Classifier: Operating System :: OS Independent
Classifier: Programming Language :: Python :: 3
Classifier: Programming Language :: Python :: 3 :: Only
Classifier: Programming Language :: Python :: 3.10
Classifier: Programming Language :: Python :: 3.12
Classifier: Programming Language :: Python :: 3.14
Classifier: Programming Language :: Python :: Implementation :: CPython
Classifier: Programming Language :: Python :: Implementation :: PyPy
Classifier: Topic :: Scientific/Engineering :: Physics
Requires-Python: >=3.8
License-File: LICENSE
Provides-Extra: tools
Requires-Dist: matplotlib>=3.5.0; extra == "tools"
Requires-Dist: numpy>=1.20.0; extra == "tools"
Requires-Dist: Pillow>=8.0.0; extra == "tools"
Dynamic: license-file
